[
    {
        "id": 1,
        "image": "../../static/salud/2f512cae-5a3e-4175-81bb-708ef219d509.jpg",
        "category": "derecho",
        "subCategory": "salud",
        "year": 2024,
        "comment": "",
        "title": "ONU y los Derechos Humanos",
        "subTitle": "",
        "active": true,
        "video": "",
        "image2": ""
    },
    {
        "id": 2,
        "image": "../../static/salud/derechos humanos y democracia.jpg",
        "category": "derecho",
        "subCategory": "salud",
        "year": 2024,
        "comment": "Lorem ipsum dolor sit amet consectetur adipisicing elit. Modi voluptatum officiis possimus. Deserunt quidem alias cumque saepe voluptatum quae blanditiis, suscipit aliquam quod aperiam harum, minus enim fugiat. Voluptas, tenetur.Impedit incidunt cupiditate sit doloremque molestias praesentium officia mollitia voluptate harum? Maxime ipsa pariatur nobis? Laboriosam natus qui delectus perspiciatis quasi quaerat ex provident fuga, culpa recusandae dolore commodi totam?Perferendis molestias magnam veniam in consectetur aliquam? Porro dolorum, suscipit asperiores quidem assumenda ipsam delectus sed, quasi nisi facilis ea qui laboriosam quam, quae dignissimos iure eum ab debitis ut?Consectetur, laboriosam omnis in aliquid quisquam eos necessitatibus animi cumque minima hic magni enim iure veritatis rerum aspernatur id sapiente laudantium. Quas eveniet similique delectus, dolor esse vel doloremque mollitia!Exercitationem aliquid deserunt laudantium iusto nobis inventore nulla, aliquam unde possimus, culpa distinctio eos illum et dignissimos nemo tenetur consequatur, vitae praesentium quam eum dicta maiores maxime fugit enim.\nLibero?Facilis voluptas omnis sequi a sint doloribus commodi dolorem ducimus consequuntur natus necessitatibus nemo sapiente et animi incidunt delectus accusamus earum optio nihil quibusdam doloremque veniam, illum exercitationem laboriosam. Necessitatibus!Quae quaerat animi porro harum aperiam distinctio repellat quis impedit, beatae blanditiis reiciendis cumque ab eaque quidem neque sed, quisquam tempora sit vel perferendis? Non maiores id temporibus vitae ex?Magnam rerum laboriosam, reiciendis quisquam eligendi aliquam facere? Cum laborum blanditiis, ex officia rem optio commodi voluptates nisi quam iusto itaque eius maiores architecto asperiores incidunt minus natus eum vero.Mollitia ducimus nulla inventore maiores perferendis officiis harum laboriosam ipsam eos quos, neque aspernatur tenetur voluptatum quasi corporis ut expedita tempore quisquam iusto vitae sequi dolorum sit iure. Laboriosam, quisquam!Magni voluptatum fugiat laudantium mollitia dignissimos. Aspernatur nihil consequatur libero atque facere, dolorem unde necessitatibus. Hic, molestias? Ad minus sint mollitia at eligendi laudantium tenetur id molestiae. Animi, optio aliquam.",
        "title": "Derechos humanos y democracia",
        "subTitle": "",
        "active": true,
        "video": "",
        "image2": ""
    },
    {
        "id": 3,
        "image": "../../static/salud/derecho a la sanidad.jpg",
        "category": "derecho",
        "subCategory": "salud",
        "year": 2024,
        "comment": "Lorem ipsum dolor sit amet consectetur adipisicing elit. Modi voluptatum officiis possimus. Deserunt quidem alias cumque saepe voluptatum quae blanditiis, suscipit aliquam quod aperiam harum, minus enim fugiat. Voluptas, tenetur.Impedit incidunt cupiditate sit doloremque molestias praesentium officia mollitia voluptate harum? Maxime ipsa pariatur nobis? Laboriosam natus qui delectus perspiciatis quasi quaerat ex provident fuga, culpa recusandae dolore commodi totam?Perferendis molestias magnam veniam in consectetur aliquam? Porro dolorum, suscipit asperiores quidem assumenda ipsam delectus sed, quasi nisi facilis ea qui laboriosam quam, quae dignissimos iure eum ab debitis ut?Consectetur, laboriosam omnis in aliquid quisquam eos necessitatibus animi cumque minima hic magni enim iure veritatis rerum aspernatur id sapiente laudantium. Quas eveniet similique delectus, dolor esse vel doloremque mollitia!Exercitationem aliquid deserunt laudantium iusto nobis inventore nulla, aliquam unde possimus, culpa distinctio eos illum et dignissimos nemo tenetur consequatur, vitae praesentium quam eum dicta maiores maxime fugit enim.\nLibero?Facilis voluptas omnis sequi a sint doloribus commodi dolorem ducimus consequuntur natus necessitatibus nemo sapiente et animi incidunt delectus accusamus earum optio nihil quibusdam doloremque veniam, illum exercitationem laboriosam. Necessitatibus!Quae quaerat animi porro harum aperiam distinctio repellat quis impedit, beatae blanditiis reiciendis cumque ab eaque quidem neque sed, quisquam tempora sit vel perferendis? Non maiores id temporibus vitae ex?Magnam rerum laboriosam, reiciendis quisquam eligendi aliquam facere? Cum laborum blanditiis, ex officia rem optio commodi voluptates nisi quam iusto itaque eius maiores architecto asperiores incidunt minus natus eum vero.Mollitia ducimus nulla inventore maiores perferendis officiis harum laboriosam ipsam eos quos, neque aspernatur tenetur voluptatum quasi corporis ut expedita tempore quisquam iusto vitae sequi dolorum sit iure. Laboriosam, quisquam!Magni voluptatum fugiat laudantium mollitia dignissimos. Aspernatur nihil consequatur libero atque facere, dolorem unde necessitatibus. Hic, molestias? Ad minus sint mollitia at eligendi laudantium tenetur id molestiae. Animi, optio aliquam.",
        "title": "Derecho a la Sanidad",
        "subTitle": "",
        "active": true,
        "video": "",
        "image2": ""
    },
    {
        "id": 4,
        "image": "../../static/penal/Manual de marca Valeria Correa.jpg",
        "category": "derecho",
        "subCategory": "penal",
        "year": 2024,
        "comment": "La cuestión del juzgamiento de delitos considerados de lesa humanidad, cometidos por aparatos organizados de poder presenta un intrincado desafío dogmático para la ciencia penal: cómo responsabilizar el accionar de aquellos que lideran las organizaciones pero que no intervienen directamente en la ejecución de los hechos, eludiendo las conceptualizaciones clásicas que fundan los institutos de la autoría y la participación criminal. Cómodamente sentados en sus escritorios, a kilómetros de distancia de los acontecimientos, los “hombres de atrás” han trazado el mapa, establecido la logística, dotado de los medios, y garantizando las impunidades, de quienes llevaban a cabo el acto físico de consumación del ilícito, únicos a los cuales se atribuía la calidad de autor, criterio central de la actuación. Las clasificaciones tradicionales no contemplaban, hasta la intervención de Claus Roxin, una figura capaz de generar una imputación adecuada, considerando las particularidades de ambos aportes o, cuanto menos, no se había diseñado hasta el momento una estructura que pudiera de contener jurídicamente un fenómeno complejo como la macrocriminalidad estatal en cuestiones de lesa humanidad.\nEl Objetivo del presente trabajo es analizar, desde el punto de vista histórico, normativo y dogmático, el impacto la teoría elaborada por Roxin frente a las categorías de autoría tradicionales, como se han afrontado algunas de las críticas mas sobresalientes (que ponen en jaque la posibilidad misma de su existencia), minuciosamente refutadas por el autor a lo largo de los años para, finalmente abordar de que manera es posible conducir, en una evolución técnico-teórica, estos contenidos al notable crecimiento del derecho punitivo aplicado a la macrocriminalidad no estatal, organizativa o empresarial, que forma parte de las agendas político criminales del mundo actual. ",
        "title": "DELITOS DE LESA HUMANIDAD",
        "subTitle": "Dominio de la voluntad por aparatos organizados de poder de Clauss Roxin.",
        "active": true,
        "video": "",
        "image2": ""
    },
    {
        "id": 5,
        "image": "../../static/salud/estudio e investigacion.JPG",
        "category": "derecho",
        "subCategory": "salud",
        "year": 2024,
        "comment": "El progreso histórico de la ciencia médica, acompañado por el desarrollo social, cultural y tecnológico, sumado al reconocimiento legal y judicial, ha elevado la salud a la categoría de derecho humano fundamental.<p><br></p>A su vez, como corpus/cuerpo normativo, el Derecho de la Salud se constituye como una rama de la ciencia jurídica cuya autonomía se ha consolidado dentro del horizonte nacional, regional y mundial, uno de los grandes desafíos de cara al Siglo XXI. Por ello resulta elemental comprender el fundamento de su reconocimiento y, además trazar su recorrido histórico y sistémico. A su vez, se vincula con el resto de los despliegues, impregnándolos de principios y valores, en una relación de transversalidad que enriquece profundamente las miradas tradicionales.<p><br></p>El escenario sanitario argentino resulta un entramado sumamente complejo, por ello abordaremos en diversas publicaciones las características de su estructura normativa y las alternativas en punto a su sistematización en el firmamento jurídico.<p><br></p>En este camino, deviene imprescindible internalizar el impacto que el crecimiento tecnológico tiene en todas las aristas del sistema de salud, y averiguar de qué manera podemos emplear los recursos de la información en una disciplina cuyo eje y centro resulta ser el ser humano. Nos enfrentamos, en esta realidad pospadémica, a tendencias que modifican paradigmáticamente los debates: catástrofes climáticas, salud mental, inteligencia artificial, necesidad de determinación de políticas públicas resilientes en contextos de profundas crisis económicas.<p><br></p>En este camino, deviene imprescindible internalizar el impacto que el crecimiento tecnológico tiene en todas las aristas del sistema de salud, y averiguar de qué manera podemos emplear los recursos de la información en una disciplina cuyo eje y centro resulta ser el ser humano. Nos enfrentamos, en esta realidad pospadémica, a tendencias que modifican paradigmáticamente los debates: catástrofes climáticas, salud mental, inteligencia artificial, necesidad de determinación de políticas públicas resilientes en contextos de profundas crisis económicas.<p><br></p>En este marco, se postula la construcción del objeto de la materia. El bioderecho, como nos explica -siempre generosamente- el maestro Miguel Angel Ciuro Caldani, resulta una realidad jurídica dotada de principios propios que deben tener reconocimiento legislativo, jurisdiccional, administrativo, científico, pedagógico, docente y académico y que han de ser valoradas por la alta capacidad que poseen para la transformación de los y las juristas.\nSus relieves transdisiciplinares ponen en diálogo los aportes de las distintas orientaciones del derecho mas, también, se nutren de otras ciencias para proveer un enfoque integral de su estudio: este área del derecho y de la vida, nos propone un catálogo de nuevos objetivos que se tensan entre lo “científicamente posible, lo éticamente aceptable y lo jurídicamente permisible”.<p><br></p>La capacitación y profundización de su estudio, constituye una propuesta de ineludible planteo para la abogacía y magistratura del nuevo milenio. ",
        "title": "Estudio e investigacion de la salud como derecho humano fundamental.",
        "subTitle": "",
        "active": true,
        "video": "",
        "image2": ""
    }
]